Workbook

Sheet Raw Data
A1: ACE Consumer products Ltd. - Financial Statement Analysis
A3: Particulars | B3: FY2023 | C3: FY2024 | D3: FY2025
A5: INCOME STATEMENT
A6: Revenue | B6: 500 | C6: 575 | D6: 680
A7: Cost of Goods Sold | B7: 300 | C7: 338 | D7: 394
A8: Gross Profit | B8: 200 | C8: 237 | D8: 286
A9: Operating Expenses | B9: 120 | C9: 140 | D9: 158
A10: Operating Profit | B10: 80 | C10: 97 | D10: 128
A11: Interest Expense | B11: 15 | C11: 17 | D11: 18
A12: Profit Before Tax | B12: 65 | C12: 80 | D12: 110
A13: Income Tax | B13: 16 | C13: 20 | D13: 28
A14: Net Profit | B14: 49 | C14: 60 | D14: 82
A16: BALANCE SHEET
A17: Cash & Cash Equivalents | B17: 60 | C17: 72 | D17: 95
A18: Accounts Receivable | B18: 75 | C18: 84 | D18: 96
A19: Inventory | B19: 90 | C19: 102 | D19: 118
A20: Other Current Assets | B20: 25 | C20: 29 | D20: 34
A21: Total Current Assets | B21: 250 | C21: 287 | D21: 343
A22: Property, Plant & Equipment | B22: 300 | C22: 335 | D22: 375
A23: Other Non-Current Assets | B23: 50 | C23: 53 | D23: 57
A24: Total Assets | B24: 600 | C24: 675 | D24: 775
A25: Accounts Payable | B25: 65 | C25: 74 | D25: 84
A26: Short-Term Debt | B26: 45 | C26: 50 | D26: 55
A27: Other Current Liabilities | B27: 40 | C27: 46 | D27: 52
A28: Total Current Liabilities | B28: 150 | C28: 170 | D28: 191
... A35: Total Liabilities & Equity | B35: 600 | C35: 675 | D35: 775
A37: CASH FLOW STATEMENT
A38: Net Profit | B38: 49 | C38: 60 | D38: 82
A39: Depreciation | B39: 25 | C39: 28 | D39: 31
A40: Change in Working Capital | B40: -10 | C40: -12 | D40: -15
A41: Cash Flow from Operating Activities | B41: 64 | C41: 76 | D41: 98
A42: Capital Expenditure | B42: -55 | C42: -63 | D42: -71
A43: Cash Flow from Investing Activities | B43: -55 | C43: -63 | D43: -71
A44: Debt Issued / (Repaid) | B44: 10 | C44: 20 | D44: 20
A45: Dividends Paid | B45: -20 | C45: -21 | D45: -24
A46: Cash Flow from Financing Activities | B46: -10 | C46: -1 | D46: -4
A47: Net Change in Cash | B47: -1 | C47: 12 | D47: 23

Sheet Income Statement
A1: ACE Consumer Products Ltd.
A2: INCOME STATEMENT
A3: For the Years FY2023–FY2025 (₹ in crore)
A5: Particulars | B5: FY2023 | C5: FY2024 | D5: FY2025
A6: Revenue | B6: ='Raw Data'!B6 -> 500 | C6: ='Raw Data'!C6 -> 575 | D6: ='Raw Data'!D6 -> 680
A7: Cost of Goods Sold | B7: ='Raw Data'!B7 -> 300 | C7: ='Raw Data'!C7 -> 338 | D7: ='Raw Data'!D7 -> 394
A8: Gross Profit | B8: =B6-B7 -> 200 | C8: =C6-C7 -> 237 | D8: =D6-D7 -> 286
A9: Operating Expenses | B9: ='Raw Data'!B9 -> 120 | C9: ='Raw Data'!C9 -> 140 | D9: ='Raw Data'!D9 -> 158
A10: Operating Profit | B10: =B8-B9 -> 80 | C10: =C8-C9 -> 97 | D10: =D8-D9 -> 128
A11: Interest Expense | B11: ='Raw Data'!B11 -> 15 | C11: ='Raw Data'!C11 -> 17 | D11: ='Raw Data'!D11 -> 18
A12: Profit Before Tax | B12: =B10-B11 -> 65 | C12: =C10-C11 -> 80 | D12: =D10-D11 -> 110
A13: Income Tax | B13: ='Raw Data'!B13 -> 16 | C13: ='Raw Data'!C13 -> 20 | D13: ='Raw Data'!D13 -> 28
A14: Net Profit | B14: =B12-B13 -> 49 | C14: =C12-C13 -> 60 | D14: =D12-D13 -> 82

Sheet Balance Sheet
A1: ACE Consumer Products Ltd.
A2: Balance Sheet
A3: For the Years FY2023–FY2025 (₹ in crore)
A5: Particulars | B5: FY2023 | C5: FY2024 | D5: FY2025
A6: ASSETS
A7: Cash & Cash Equivalents | B7: ='Raw Data'!B17 -> 60 | C7: ='Raw Data'!C17 -> 72 | D7: ='Raw Data'!D17 -> 95
A8: Accounts Receivable | B8: ='Raw Data'!B18 -> 75 | C8: ='Raw Data'!C18 -> 84 | D8: ='Raw Data'!D18 -> 96
A9: Inventory | B9: ='Raw Data'!B19 -> 90 | C9: ='Raw Data'!C19 -> 102 | D9: ='Raw Data'!D19 -> 118
A10: Other Current Assets | B10: ='Raw Data'!B20 -> 25 | C10: ='Raw Data'!C20 -> 29 | D10: ='Raw Data'!D20 -> 34
A11: Total Current Assets | B11: =SUM(B7:B10) -> 250 | C11: =SUM(C7:C10) -> 287 | D11: =SUM(D7:D10) -> 343
A12: Property, Plant & Equipment | B12: ='Raw Data'!B22 -> 300 | C12: ='Raw Data'!C22 -> 335 | D12: ='Raw Data'!D22 -> 375
A13: Other Non-Current Assets | B13: ='Raw Data'!B23 -> 50 | C13: ='Raw Data'!C23 -> 53 | D13: ='Raw Data'!D23 -> 57
A14: Total Assets | B14: =B11+B12+B13 -> 600 | C14: =C11+C12+C13 -> 675 | D14: =D11+D12+D13 -> 775
A15: LIABILITIES
A16: Accounts Payable | B16: ='Raw Data'!B25 -> 65 | C16: ='Raw Data'!C25 -> 74 | D16: ='Raw Data'!D25 -> 84
A17: Short-Term Debt | B17: ='Raw Data'!B26 -> 45 | C17: ='Raw Data'!C26 -> 50 | D17: ='Raw Data'!D26 -> 55
A18: Other Current Liabilities | B18: ='Raw Data'!B27 -> 40 | C18: ='Raw Data'!C27 -> 46 | D18: ='Raw Data'!D27 -> 52
A19: Total Current Liabilities | B19: =B16+B17+B18 -> 150 | C19: =C16+C17+C18 -> 170 | D19: =D16+D17+D18 -> 191
A20: Long-Term Debt | B20: ='Raw Data'!B29 -> 180 | C20: ='Raw Data'!C29 -> 195 | D20: ='Raw Data'!D29 -> 210
A21: Other Non-Current Liabilities | B21: ='Raw Data'!B30 -> 50 | C21: ='Raw Data'!C30 -> 55 | D21: ='Raw Data'!D30 -> 59
A22: Total Liabilities | B22: =SUM(B19:B21) -> 380 | C22: =SUM(C19:C21) -> 420 | D22: =SUM(D19:D21) -> 460
A23: Share Capital | B23: ='Raw Data'!B32 -> 100 | C23: ='Raw Data'!C32 -> 100 | D23: ='Raw Data'!D32 -> 100
A24: Retained Earnings | B24: ='Raw Data'!B33 -> 120 | C24: ='Raw Data'!C33 -> 155 | D24: ='Raw Data'!D33 -> 215
A25: Total Equity | B25: =B23+B24 -> 220 | C25: =C23+C24 -> 255 | D25: =D23+D24 -> 315
A26: Total Liabilities & Equity | B26: =SUM(B22,B25) -> 600 | C26: =SUM(C22,C25) -> 675 | D26: =SUM(D22,D25) -> 775

Sheet Cash Flow
A1: ACE Consumer Products Ltd.
A2: Cash Flow Statement
A3: For the Years FY2023–FY2025 (₹ In crore)
A5: Particulars | B5: FY2023 | C5: FY2024 | D5: FY2025
A6: Net Profit | B6: ='Raw Data'!B38 -> 49 | C6: ='Raw Data'!C38 -> 60 | D6: ='Raw Data'!D38 -> 82
A7: Depreciation | B7: ='Raw Data'!B39 -> 25 | C7: ='Raw Data'!C39 -> 28 | D7: ='Raw Data'!D39 -> 31
A8: Change in Working Capital | B8: ='Raw Data'!B40 -> -10 | C8: ='Raw Data'!C40 -> -12 | D8: ='Raw Data'!D40 -> -15
A9: Cash Flow from Operating Activities | B9: =SUM(B6:B8) -> 64 | C9: =SUM(C6:C8) -> 76 | D9: =SUM(D6:D8) -> 98
A10: Capital Expenditure | B10: ='Raw Data'!B42 -> -55 | C10: ='Raw Data'!C42 -> -63 | D10: ='Raw Data'!D42 -> -71
A11: Cash Flow from Investing Activities | B11: =B10 -> -55 | C11: =C10 -> -63 | D11: =D10 -> -71
A12: Debt Issued / (Repaid) | B12: ='Raw Data'!B44 -> 10 | C12: ='Raw Data'!C44 -> 20 | D12: ='Raw Data'!D44 -> 20
A13: Dividends Paid | B13: ='Raw Data'!B45 -> -20 | C13: ='Raw Data'!C45 -> -21 | D13: ='Raw Data'!D45 -> -24
A14: Cash Flow from Financing Activities | B14: =SUM(B12:B13) -> -10 | C14: =SUM(C12:C13) -> -1 | D14: =SUM(D12:D13) -> -4
A15: Net Change in Cash | B15: =SUM(B9,B11,B14) -> -1 | C15: =SUM(C9,C11,C14) -> 12 | D15: =SUM(D9,D11,D14) -> 23

Sheet Ratio Analysis
A1: ACE Consumer Products Ltd.
A2: Ratio Analysis
A3: FY2023–FY2025 (₹ In crore)
A5: PROFITABILITY RATIOS | B5: FY2023 | C5: FY2024 | D5: FY2025
A6: Gross Profit Margin | B6: ='Income Statement'!B8/'Income Statement'!B6 -> 0.4 | C6: ='Income Statement'!C8/'Income Statement'!C6 -> 0.41217391 | D6: ='Income Statement'!D8/'Income Statement'!D6 -> 0.42058824
A7: Operating Profit Margin | B7: ='Income Statement'!B10/'Income Statement'!B6 -> 0.16 | C7: ='Income Statement'!C10/'Income Statement'!C6 -> 0.16869565 | D7: ='Income Statement'!D10/'Income Statement'!D6 -> 0.18823529
A8: Net Profit Margin | B8: ='Income Statement'!B14/'Income Statement'!B6 -> 0.098 | C8: ='Income Statement'!C14/'Income Statement'!C6 -> 0.10434783 | D8: ='Income Statement'!D14/'Income Statement'!D6 -> 0.12058824
A9: Return on Assets (ROA) | B9: ='Income Statement'!B14/'Balance Sheet'!B14 -> 0.081666667 | C9: ='Income Statement'!C14/'Balance Sheet'!C14 -> 0.088888889 | D9: ='Income Statement'!D14/'Balance Sheet'!D14 -> 0.10580645
A10: Return on Equity (ROE) | B10: ='Income Statement'!B14/'Balance Sheet'!B25 -> 0.22272727 | C10: ='Income Statement'!C14/'Balance Sheet'!C25 -> 0.23529412 | D10: ='Income Statement'!D14/'Balance Sheet'!D25 -> 0.26031746
A12: LIQUIDITY RATIOS | B12: FY2023 | C12: FY2024 | D12: FY2025
A13: Current Ratio | B13: ='Balance Sheet'!B11/'Balance Sheet'!B19 -> 1.6666667 | C13: ='Balance Sheet'!C11/'Balance Sheet'!C19 -> 1.6882353 | D13: ='Balance Sheet'!D11/'Balance Sheet'!D19 -> 1.7958115
A14: Quick Ratio | B14: =('Balance Sheet'!B11-'Balance Sheet'!B9)/'Balance Sheet'!B19 -> 1.0666667 | C14: =('Balance Sheet'!C11-'Balance Sheet'!C9)/'Balance Sheet'!C19 -> 1.0882353 | D14: =('Balance Sheet'!D11-'Balance Sheet'!D9)/'Balance Sheet'!D19 -> 1.1780105
A16: LEVERAGE RATIOS | B16: FY2023 | C16: FY2024 | D16: FY2025
A17: Debt-to-Equity Ratio | B17: =('Balance Sheet'!B17+'Balance Sheet'!B20)/'Balance Sheet'!B25 -> 1.0227273 | C17: =('Balance Sheet'!C17+'Balance Sheet'!C20)/'Balance Sheet'!C25 -> 0.96078431 | D17: =('Balance Sheet'!D17+'Balance Sheet'!D20)/'Balance Sheet'!D25 -> 0.84126984
A18: Interest Coverage Ratio | B18: ='Income Statement'!B10/'Income Statement'!B11 -> 5.3333333 | C18: ='Income Statement'!C10/'Income Statement'!C11 -> 5.7058824 | D18: ='Income Statement'!D10/'Income Statement'!D11 -> 7.1111111
A19: Debt-to-Assets Ratio | B19: =('Balance Sheet'!B17+'Balance Sheet'!B20)/'Balance Sheet'!B14 -> 0.375 | C19: =('Balance Sheet'!C17+'Balance Sheet'!C20)/'Balance Sheet'!C14 -> 0.36296296 | D19: =('Balance Sheet'!D17+'Balance Sheet'!D20)/'Balance Sheet'!D14 -> 0.34193548 | K19: {=+K19:Q19} -> 0

Sheet Dashboard
A1: ACE Consumer Products Ltd.
A2: Financial Analysis Dashboard
A3: FY2023–FY2025 | ₹ In crore
A4: Key Performance Indicators (KPIs)
A5: Revenue (FY2025) | B5: ='Income Statement'!D6 -> 680
A6: Net Profit (FY2025) | B6: ='Income Statement'!D14 -> 82
A7: Net Profit Margin | B7: ='Ratio Analysis'!D8 -> 0.12058824
A10: YEAR | B10: REVENUE | D10: YEAR | E10: NET PROFIT | G10: YEAR | H10: NET PROFIT MARGIN
A11: FY2023 | B11: ='Income Statement'!B6 -> 500 | D11: FY2023 | E11: ='Income Statement'!B14 -> 49 | G11: FY2023 | H11: ='Ratio Analysis'!B8 -> 0.098
A12: FY2024 | B12: ='Income Statement'!C6 -> 575 | D12: FY2024 | E12: ='Income Statement'!C14 -> 60 | G12: FY2024 | H12: ='Ratio Analysis'!C8 -> 0.10434783
A13: FY2025 | B13: ='Income Statement'!D6 -> 680 | D13: FY2025 | E13: ='Income Statement'!D14 -> 82 | G13: FY2025 | H13: ='Ratio Analysis'!D8 -> 0.12058824
A26: Financial Analysis & Insights
A27: Area | B27: Conclusion
A28: Revenue | B28: Strong growth from FY2023 to FY2025
A29: Profitability | B29: Profit margins improved
A30: Liquidity | B30: Short-term financial position improved
A31: Leverage | B31: Debt-to-equity declined
A32: Overall | B32: Financial performance improved over the period
A34: Author: Vinay L | Tool: Microsoft Excel | Project: Financial Statement Analysis
